{
  "SQM": {
    "accion": "VENDER",
    "cantidad": 112,
    "precio_entrada": 88.79000091552734,
    "sl": 96.0,
    "tp": 74.38,
    "tipo": "Acci\u00f3n USA/Chile",
    "fecha_entrada": "2026-04-27T09:21:05.497966",
    "horizonte": "1\u20137 d\u00edas",
    "conviccion": 91.7,
    "order_ids": [
      4,
      5,
      6
    ]
  },
  "COPEC": {
    "accion": "VENDER",
    "cantidad": 1,
    "precio_entrada": 6515.0,
    "sl": 6864.37,
    "tp": 5816.26,
    "tipo": "Acci\u00f3n Chile",
    "fecha_entrada": "2026-04-29T09:30:31.633602",
    "horizonte": "1\u20132 semanas",
    "conviccion": 84.5,
    "order_ids": [
      7,
      8,
      9
    ]
  }
}